MANIFEST.in
README.md
setup.cfg
setup.py
amqcfg/__init__.py
amqcfg/amqcfg.py
amqcfg/amqcfg_cli.py
amqcfg/cli_arguments.py
amqcfg/config_data.py
amqcfg/exceptions.py
amqcfg/files.py
amqcfg/logger_settings.py
amqcfg/meta.py
amqcfg/output.py
amqcfg/profiles.py
amqcfg/query.py
amqcfg/templates.py
amqcfg.egg-info/PKG-INFO
amqcfg.egg-info/SOURCES.txt
amqcfg.egg-info/dependency_links.txt
amqcfg.egg-info/entry_points.txt
amqcfg.egg-info/requires.txt
amqcfg.egg-info/top_level.txt
amqcfg/profiles/amq_broker/7.2.0/AIOBasic.yaml
amqcfg/profiles/amq_broker/7.2.0/NIOBasic.yaml
amqcfg/profiles/amq_broker/7.2.0/default.yaml
amqcfg/profiles/amq_broker/7.2.0/_modules/bootstrap_xml/allow.yaml
amqcfg/profiles/amq_broker/7.2.0/cluster/on_demand.yaml
amqcfg/profiles/amq_broker/7.2.0/cluster/on_demand_redistribution.yaml
amqcfg/profiles/amq_broker/7.2.0/cluster/strict.yaml
amqcfg/profiles/amq_broker/7.2.0/ha/replication.yaml
amqcfg/profiles/amq_broker/7.2.0/ha/shared_store_fs.yaml
amqcfg/profiles/amq_broker/7.2.0/ha/shared_store_jdbc.yaml
amqcfg/profiles/amq_broker/7.2.0/performance/base.yaml
amqcfg/profiles/amq_broker/7.2.0/performance/perf-clustering.yaml
amqcfg/profiles/amq_broker/7.2.0/store/jdbc/default.yaml
amqcfg/profiles/artemis/2.5.0/AIOBasic.yaml
amqcfg/profiles/artemis/2.5.0/NIOBasic.yaml
amqcfg/profiles/artemis/2.5.0/default.yaml
amqcfg/profiles/artemis/2.5.0/showcase.yaml
amqcfg/profiles/artemis/2.5.0/_modules/artemis_profile/default.yaml
amqcfg/profiles/artemis/2.5.0/_modules/artemis_profile/default_jmx.yaml
amqcfg/profiles/artemis/2.5.0/_modules/artemis_profile/performance_baseline.yaml
amqcfg/profiles/artemis/2.5.0/_modules/artemis_profile/performance_params.yaml
amqcfg/profiles/artemis/2.5.0/_modules/artemis_profile/performance/_selector.yaml
amqcfg/profiles/artemis/2.5.0/_modules/bootstrap_xml/allow.yaml
amqcfg/profiles/artemis/2.5.0/_modules/bootstrap_xml/default.yaml
amqcfg/profiles/artemis/2.5.0/_modules/broker_xml/critical_analyzer_default.yaml
amqcfg/profiles/artemis/2.5.0/_modules/broker_xml/acceptors/default.yaml
amqcfg/profiles/artemis/2.5.0/_modules/broker_xml/acceptors/simplified.yaml
